Workbook

Sheet Dashboard
A1: CASH FLOW FORECASTER
A2: 12-Month Cash Flow Projection & Scenario Planning
A4: EXECUTIVE SUMMARY
A6: Metric | B6: Realistic Scenario | C6: Optimistic | D6: Pessimistic
A7: Starting Cash Balance | B7: =Inputs!B5 | C7: =Inputs!B5 | D7: =Inputs!B5
A8: Total Cash Inflows (12mo) | B8: =SUM(Realistic!C5:N5) | C8: =SUM(Optimistic!C5:N5) | D8: =SUM(Pessimistic!C5:N5)
A9: Total Cash Outflows (12mo) | B9: =SUM(Realistic!C20:N20) | C9: =SUM(Optimistic!C20:N20) | D9: =SUM(Pessimistic!C20:N20)
A10: Net Cash Flow | B10: =B8-B9 | C10: =C8-C9 | D10: =D8-D9
A11: Ending Cash Balance | B11: =B7+B10 | C11: =C7+C10 | D11: =D7+D10
A12: Lowest Cash Point | B12: =MIN(Realistic!C22:N22) | C12: =MIN(Optimistic!C22:N22) | D12: =MIN(Pessimistic!C22:N22)
A13: Month of Lowest Cash | B13: =INDEX(Realistic!C4:N4,MATCH(B12,Realistic!C22:N22,0)) | C13: =INDEX(Optimistic!C4:N4,MATCH(C12,Optimistic!C22:N22,0)) | D13: =INDEX(Pessimistic!C4:N4,MATCH(D12,Pessimistic!C22:N22,0))
A16: ⚠️ CASH SHORTAGE ALERTS
A17: If cash balance drops below: | B17: =Inputs!B6
A18: Alert Status (Realistic): | B18: =IF(Dashboard!B12<Dashboard!B16,"🔴 ACTION REQUIRED","✅ On Track")
A19: Recommended Action Date: | B19: =IF(B17="🔴 ACTION REQUIRED",Dashboard!B13&" - Start fundraising 60 days prior","N/A")

Sheet Inputs
A1: DATA INPUTS
A2: Enter your business data in the YELLOW cells
A4: BUSINESS INFORMATION
A5: Starting Cash Balance | B5: 50000 | D5: How much cash you have today
A6: Minimum Cash Alert Level | B6: 15000 | D6: Alert when cash drops below this
A8: REVENUE ASSUMPTIONS
A9: Monthly Revenue (Current) | B9: 25000 | D9: Your current monthly revenue
A10: Revenue Growth Rate (Optimistic) | B10: 0.15 | D10: 15% = 0.15
A11: Revenue Growth Rate (Realistic) | B11: 0.08 | D11: 8% = 0.08
A12: Revenue Growth Rate (Pessimistic) | B12: 0.03 | D12: 3% = 0.03
A13: Seasonal Factor - Q1 | B13: 0.85 | D13: 0.85 = 15% below average
A14: Seasonal Factor - Q2 | B14: 1 | D14: 1.00 = average
A15: Seasonal Factor - Q3 | B15: 0.95 | D15: 0.95 = 5% below average
A16: Seasonal Factor - Q4 | B16: 1.2 | D16: 1.20 = 20% above average
A18: EXPENSE ASSUMPTIONS
A19: Monthly Operating Expenses | B19: 18000 | D19: Rent, payroll, utilities, etc.
A20: Expense Growth Rate (Annual) | B20: 0.05 | D20: 5% = 0.05
A21: One-time Expenses (if any) | B21: 0 | D21: Equipment, hiring, etc.
A22: One-time Expense Month | B22: 6 | D22: Month 1-12

Sheet Realistic
A1: REALISTIC SCENARIO
A2: 12-Month Cash Flow Projection
A4: Month | B4: Starting | C4: Jan 2026 | D4: Jan 2026 | E4: Mar 2026 | F4: Apr 2026 | G4: May 2026 | H4: May 2026 | I4: Jun 2026 | J4: Jul 2026 | K4: Aug 2026 | L4: Sep 2026 | M4: Oct 2026 | N4: Nov 2026
A5: CASH INFLOWS
A6: Revenue (with seasonality) | C6: =Inputs!$B$9*Inputs!$B$10 | D6: =C6*(1+Inputs!$B$11)*Inputs!$B$10 | E6: =D6*(1+Inputs!$B$11)*Inputs!$B$10 | F6: =E6*(1+Inputs!$B$11)*Inputs!$B$11 | G6: =F6*(1+Inputs!$B$11)*Inputs!$B$11 | H6: =G6*(1+Inputs!$B$11)*Inputs!$B$11 | I6: =H6*(1+Inputs!$B$11)*Inputs!$B$12 | J6: =I6*(1+Inputs!$B$11)*Inputs!$B$12 | K6: =J6*(1+Inputs!$B$11)*Inputs!$B$12 | L6: =K6*(1+Inputs!$B$11)*Inputs!$B$13 | M6: =L6*(1+Inputs!$B$11)*Inputs!$B$13 | N6: =M6*(1+Inputs!$B$11)*Inputs!$B$13
A7: Other Income | C7: 0 | D7: 0 | E7: 0 | F7: 0 | G7: 0 | H7: 0 | I7: 0 | J7: 0 | K7: 0 | L7: 0 | M7: 0 | N7: 0
A8: Total Inflows | C8: =C6+C7 | D8: =D6+D7 | E8: =E6+E7 | F8: =F6+F7 | G8: =G6+G7 | H8: =H6+H7 | I8: =I6+I7 | J8: =J6+J7 | ... N8: =N6+N7
A10: CASH OUTFLOWS
A11: Operating Expenses | C11: =Inputs!$B$19*(1+Inputs!$B$20/12)^0 | D11: =Inputs!$B$19*(1+Inputs!$B$20/12)^1 | E11: =Inputs!$B$19*(1+Inputs!$B$20/12)^2 | F11: =Inputs!$B$19*(1+Inputs!$B$20/12)^3 | G11: =Inputs!$B$19*(1+Inputs!$B$20/12)^4 | H11: =Inputs!$B$19*(1+Inputs!$B$20/12)^5 | I11: =Inputs!$B$19*(1+Inputs!$B$20/12)^6 | J11: =Inputs!$B$19*(1+Inputs!$B$20/12)^7 | K11: =Inputs!$B$19*(1+Inputs!$B$20/12)^8 | L11: =Inputs!$B$19*(1+Inputs!$B$20/12)^9 | M11: =Inputs!$B$19*(1+Inputs!$B$20/12)^10 | N11: =Inputs!$B$19*(1+Inputs!$B$20/12)^11
A12: One-time Expenses | C12: =IF(1=Inputs!$B$22,Inputs!$B$21,0) | D12: =IF(2=Inputs!$B$22,Inputs!$B$21,0) | E12: =IF(3=Inputs!$B$22,Inputs!$B$21,0) | F12: =IF(4=Inputs!$B$22,Inputs!$B$21,0) | G12: =IF(5=Inputs!$B$22,Inputs!$B$21,0) | H12: =IF(6=Inputs!$B$22,Inputs!$B$21,0) | I12: =IF(7=Inputs!$B$22,Inputs!$B$21,0) | J12: =IF(8=Inputs!$B$22,Inputs!$B$21,0) | K12: =IF(9=Inputs!$B$22,Inputs!$B$21,0) | L12: =IF(10=Inputs!$B$22,Inputs!$B$21,0) | M12: =IF(11=Inputs!$B$22,Inputs!$B$21,0) | N12: =IF(12=Inputs!$B$22,Inputs!$B$21,0)
A13: Marketing & Sales | C13: =C6*0.15 | D13: =D6*0.15 | E13: =E6*0.15 | F13: =F6*0.15 | G13: =G6*0.15 | H13: =H6*0.15 | I13: =I6*0.15 | J13: =J6*0.15 | ... N13: =N6*0.15
A14: Total Outflows | C14: =SUM(C11:C13) | D14: =SUM(D11:D13) | E14: =SUM(E11:E13) | F14: =SUM(F11:F13) | G14: =SUM(G11:G13) | H14: =SUM(H11:H13) | I14: =SUM(I11:I13) | J14: =SUM(J11:J13) | ... N14: =SUM(N11:N13)
A16: NET CASH FLOW | C16: =C8-C20 | D16: =D8-D20 | E16: =E8-E20 | F16: =F8-F20 | G16: =G8-G20 | H16: =H8-H20 | I16: =I8-I20 | J16: =J8-J20 | ... N16: =N8-N20
A17: ENDING CASH BALANCE | B17: =Inputs!$B$5 | C17: =B17+C16 | D17: =C17+D16 | E17: =D17+E16 | F17: =E17+F16 | G17: =F17+G16 | H17: =G17+H16 | I17: =H17+I16 | J17: =I17+J16 | ... N17: =M17+N16

Sheet Optimistic
A1: OPTIMISTIC SCENARIO
A2: 12-Month Cash Flow Projection
A4: Month | B4: Starting | C4: Jan 2026 | D4: Jan 2026 | E4: Mar 2026 | F4: Apr 2026 | G4: May 2026 | H4: May 2026 | I4: Jun 2026 | J4: Jul 2026 | K4: Aug 2026 | L4: Sep 2026 | M4: Oct 2026 | N4: Nov 2026
A5: CASH INFLOWS
A6: Revenue (with seasonality) | C6: =Inputs!$B$9*Inputs!$B$10 | D6: =C6*(1+Inputs!$B$10)*Inputs!$B$10 | E6: =D6*(1+Inputs!$B$10)*Inputs!$B$10 | F6: =E6*(1+Inputs!$B$10)*Inputs!$B$11 | G6: =F6*(1+Inputs!$B$10)*Inputs!$B$11 | H6: =G6*(1+Inputs!$B$10)*Inputs!$B$11 | I6: =H6*(1+Inputs!$B$10)*Inputs!$B$12 | J6: =I6*(1+Inputs!$B$10)*Inputs!$B$12 | K6: =J6*(1+Inputs!$B$10)*Inputs!$B$12 | L6: =K6*(1+Inputs!$B$10)*Inputs!$B$13 | M6: =L6*(1+Inputs!$B$10)*Inputs!$B$13 | N6: =M6*(1+Inputs!$B$10)*Inputs!$B$13
A7: Other Income | C7: 0 | D7: 0 | E7: 0 | F7: 0 | G7: 0 | H7: 0 | I7: 0 | J7: 0 | K7: 0 | L7: 0 | M7: 0 | N7: 0
A8: Total Inflows | C8: =C6+C7 | D8: =D6+D7 | E8: =E6+E7 | F8: =F6+F7 | G8: =G6+G7 | H8: =H6+H7 | I8: =I6+I7 | J8: =J6+J7 | ... N8: =N6+N7
A10: CASH OUTFLOWS
A11: Operating Expenses | C11: =Inputs!$B$19*(1+Inputs!$B$20/12)^0 | D11: =Inputs!$B$19*(1+Inputs!$B$20/12)^1 | E11: =Inputs!$B$19*(1+Inputs!$B$20/12)^2 | F11: =Inputs!$B$19*(1+Inputs!$B$20/12)^3 | G11: =Inputs!$B$19*(1+Inputs!$B$20/12)^4 | H11: =Inputs!$B$19*(1+Inputs!$B$20/12)^5 | I11: =Inputs!$B$19*(1+Inputs!$B$20/12)^6 | J11: =Inputs!$B$19*(1+Inputs!$B$20/12)^7 | K11: =Inputs!$B$19*(1+Inputs!$B$20/12)^8 | L11: =Inputs!$B$19*(1+Inputs!$B$20/12)^9 | M11: =Inputs!$B$19*(1+Inputs!$B$20/12)^10 | N11: =Inputs!$B$19*(1+Inputs!$B$20/12)^11
A12: One-time Expenses | C12: =IF(1=Inputs!$B$22,Inputs!$B$21,0) | D12: =IF(2=Inputs!$B$22,Inputs!$B$21,0) | E12: =IF(3=Inputs!$B$22,Inputs!$B$21,0) | F12: =IF(4=Inputs!$B$22,Inputs!$B$21,0) | G12: =IF(5=Inputs!$B$22,Inputs!$B$21,0) | H12: =IF(6=Inputs!$B$22,Inputs!$B$21,0) | I12: =IF(7=Inputs!$B$22,Inputs!$B$21,0) | J12: =IF(8=Inputs!$B$22,Inputs!$B$21,0) | K12: =IF(9=Inputs!$B$22,Inputs!$B$21,0) | L12: =IF(10=Inputs!$B$22,Inputs!$B$21,0) | M12: =IF(11=Inputs!$B$22,Inputs!$B$21,0) | N12: =IF(12=Inputs!$B$22,Inputs!$B$21,0)
A13: Marketing & Sales | C13: =C6*0.15 | D13: =D6*0.15 | E13: =E6*0.15 | F13: =F6*0.15 | G13: =G6*0.15 | H13: =H6*0.15 | I13: =I6*0.15 | J13: =J6*0.15 | ... N13: =N6*0.15
A14: Total Outflows | C14: =SUM(C11:C13) | D14: =SUM(D11:D13) | E14: =SUM(E11:E13) | F14: =SUM(F11:F13) | G14: =SUM(G11:G13) | H14: =SUM(H11:H13) | I14: =SUM(I11:I13) | J14: =SUM(J11:J13) | ... N14: =SUM(N11:N13)
A16: NET CASH FLOW | C16: =C8-C20 | D16: =D8-D20 | E16: =E8-E20 | F16: =F8-F20 | G16: =G8-G20 | H16: =H8-H20 | I16: =I8-I20 | J16: =J8-J20 | ... N16: =N8-N20
A17: ENDING CASH BALANCE | B17: =Inputs!$B$5 | C17: =B17+C16 | D17: =C17+D16 | E17: =D17+E16 | F17: =E17+F16 | G17: =F17+G16 | H17: =G17+H16 | I17: =H17+I16 | J17: =I17+J16 | ... N17: =M17+N16

Sheet Pessimistic
A1: PESSIMISTIC SCENARIO
A2: 12-Month Cash Flow Projection
A4: Month | B4: Starting | C4: Jan 2026 | D4: Jan 2026 | E4: Mar 2026 | F4: Apr 2026 | G4: May 2026 | H4: May 2026 | I4: Jun 2026 | J4: Jul 2026 | K4: Aug 2026 | L4: Sep 2026 | M4: Oct 2026 | N4: Nov 2026
A5: CASH INFLOWS
A6: Revenue (with seasonality) | C6: =Inputs!$B$9*Inputs!$B$10 | D6: =C6*(1+Inputs!$B$12)*Inputs!$B$10 | E6: =D6*(1+Inputs!$B$12)*Inputs!$B$10 | F6: =E6*(1+Inputs!$B$12)*Inputs!$B$11 | G6: =F6*(1+Inputs!$B$12)*Inputs!$B$11 | H6: =G6*(1+Inputs!$B$12)*Inputs!$B$11 | I6: =H6*(1+Inputs!$B$12)*Inputs!$B$12 | J6: =I6*(1+Inputs!$B$12)*Inputs!$B$12 | K6: =J6*(1+Inputs!$B$12)*Inputs!$B$12 | L6: =K6*(1+Inputs!$B$12)*Inputs!$B$13 | M6: =L6*(1+Inputs!$B$12)*Inputs!$B$13 | N6: =M6*(1+Inputs!$B$12)*Inputs!$B$13
A7: Other Income | C7: 0 | D7: 0 | E7: 0 | F7: 0 | G7: 0 | H7: 0 | I7: 0 | J7: 0 | K7: 0 | L7: 0 | M7: 0 | N7: 0
A8: Total Inflows | C8: =C6+C7 | D8: =D6+D7 | E8: =E6+E7 | F8: =F6+F7 | G8: =G6+G7 | H8: =H6+H7 | I8: =I6+I7 | J8: =J6+J7 | ... N8: =N6+N7
A10: CASH OUTFLOWS
A11: Operating Expenses | C11: =Inputs!$B$19*(1+Inputs!$B$20/12)^0 | D11: =Inputs!$B$19*(1+Inputs!$B$20/12)^1 | E11: =Inputs!$B$19*(1+Inputs!$B$20/12)^2 | F11: =Inputs!$B$19*(1+Inputs!$B$20/12)^3 | G11: =Inputs!$B$19*(1+Inputs!$B$20/12)^4 | H11: =Inputs!$B$19*(1+Inputs!$B$20/12)^5 | I11: =Inputs!$B$19*(1+Inputs!$B$20/12)^6 | J11: =Inputs!$B$19*(1+Inputs!$B$20/12)^7 | K11: =Inputs!$B$19*(1+Inputs!$B$20/12)^8 | L11: =Inputs!$B$19*(1+Inputs!$B$20/12)^9 | M11: =Inputs!$B$19*(1+Inputs!$B$20/12)^10 | N11: =Inputs!$B$19*(1+Inputs!$B$20/12)^11
A12: One-time Expenses | C12: =IF(1=Inputs!$B$22,Inputs!$B$21,0) | D12: =IF(2=Inputs!$B$22,Inputs!$B$21,0) | E12: =IF(3=Inputs!$B$22,Inputs!$B$21,0) | F12: =IF(4=Inputs!$B$22,Inputs!$B$21,0) | G12: =IF(5=Inputs!$B$22,Inputs!$B$21,0) | H12: =IF(6=Inputs!$B$22,Inputs!$B$21,0) | I12: =IF(7=Inputs!$B$22,Inputs!$B$21,0) | J12: =IF(8=Inputs!$B$22,Inputs!$B$21,0) | K12: =IF(9=Inputs!$B$22,Inputs!$B$21,0) | L12: =IF(10=Inputs!$B$22,Inputs!$B$21,0) | M12: =IF(11=Inputs!$B$22,Inputs!$B$21,0) | N12: =IF(12=Inputs!$B$22,Inputs!$B$21,0)
A13: Marketing & Sales | C13: =C6*0.15 | D13: =D6*0.15 | E13: =E6*0.15 | F13: =F6*0.15 | G13: =G6*0.15 | H13: =H6*0.15 | I13: =I6*0.15 | J13: =J6*0.15 | ... N13: =N6*0.15
A14: Total Outflows | C14: =SUM(C11:C13) | D14: =SUM(D11:D13) | E14: =SUM(E11:E13) | F14: =SUM(F11:F13) | G14: =SUM(G11:G13) | H14: =SUM(H11:H13) | I14: =SUM(I11:I13) | J14: =SUM(J11:J13) | ... N14: =SUM(N11:N13)
A16: NET CASH FLOW | C16: =C8-C20 | D16: =D8-D20 | E16: =E8-E20 | F16: =F8-F20 | G16: =G8-G20 | H16: =H8-H20 | I16: =I8-I20 | J16: =J8-J20 | ... N16: =N8-N20
A17: ENDING CASH BALANCE | B17: =Inputs!$B$5 | C17: =B17+C16 | D17: =C17+D16 | E17: =D17+E16 | F17: =E17+F16 | G17: =F17+G16 | H17: =G17+H16 | I17: =H17+I16 | J17: =I17+J16 | ... N17: =M17+N16

Sheet Instructions
A1: HOW TO USE THIS CASH FLOW FORECASTER
A4: QUICK START
A5: 1. Go to the "Inputs" sheet
A6: 2. Enter your data in the YELLOW cells
A7: 3. Go to "Dashboard" to see your 12-month forecast
A8: 4. Review all 3 scenarios: Realistic, Optimistic, Pessimistic
A10: UNDERSTANDING THE SCENARIOS
A12: Realistic: Your best estimate of likely performance (8% growth)
A13: Optimistic: Best-case scenario if things go well (15% growth)
A14: Pessimistic: Worst-case if things go poorly (3% growth)
A16: KEY METRICS EXPLAINED
A18: Net Cash Flow: Revenue minus expenses each month
... A51: Created: January 2026
