Workbook

Sheet Inputs
A1: BUSINESS INPUTS
A2: Enter your data in the YELLOW cells below
A3: Description | B3: Amount
A4: Starting Cash | B4: 50000
A6: MONTHLY REVENUE
A7: Current Monthly Revenue | B7: 25000
A8: Revenue Growth % (monthly) | B8: 0.05
A10: MONTHLY EXPENSES
A11: Salary & Payroll | B11: 12000
A12: Rent & Facilities | B12: 3000
A13: Marketing & Sales | B13: 2500
A14: Software & Tools | B14: 800
A15: Other Operating Expenses | B15: 1700

Sheet 12-Month Forecast
A1: 12-MONTH CASH FLOW FORECAST
B3: Starting | C3: Jan 26 | D3: Jan 26 | E3: Mar 26 | F3: Apr 26 | G3: May 26 | H3: May 26 | I3: Jun 26 | J3: Jul 26 | K3: Aug 26 | L3: Sep 26 | M3: Oct 26 | N3: Nov 26
A5: REVENUE
A6: Monthly Revenue | C6: =Inputs!$B$5 | D6: =C6*(1+Inputs!$B$6) | E6: =D6*(1+Inputs!$B$6) | F6: =E6*(1+Inputs!$B$6) | G6: =F6*(1+Inputs!$B$6) | H6: =G6*(1+Inputs!$B$6) | I6: =H6*(1+Inputs!$B$6) | J6: =I6*(1+Inputs!$B$6) | K6: =J6*(1+Inputs!$B$6) | ... N6: =M6*(1+Inputs!$B$6)
A7: Total Revenue | C7: =C6 | D7: =D6 | E7: =E6 | F7: =F6 | G7: =G6 | H7: =H6 | I7: =I6 | J7: =J6 | ... N7: =N6
A9: EXPENSES
A10: Salary & Payroll | C10: =Inputs!$B$9 | D10: =Inputs!$B$9 | E10: =Inputs!$B$9 | F10: =Inputs!$B$9 | G10: =Inputs!$B$9 | H10: =Inputs!$B$9 | I10: =Inputs!$B$9 | J10: =Inputs!$B$9 | ... N10: =Inputs!$B$9
A11: Rent & Facilities | C11: =Inputs!$B$10 | D11: =Inputs!$B$10 | E11: =Inputs!$B$10 | F11: =Inputs!$B$10 | G11: =Inputs!$B$10 | H11: =Inputs!$B$10 | I11: =Inputs!$B$10 | J11: =Inputs!$B$10 | ... N11: =Inputs!$B$10
A12: Marketing & Sales | C12: =Inputs!$B$11 | D12: =Inputs!$B$11 | E12: =Inputs!$B$11 | F12: =Inputs!$B$11 | G12: =Inputs!$B$11 | H12: =Inputs!$B$11 | I12: =Inputs!$B$11 | J12: =Inputs!$B$11 | ... N12: =Inputs!$B$11
A13: Software & Tools | C13: =Inputs!$B$12 | D13: =Inputs!$B$12 | E13: =Inputs!$B$12 | F13: =Inputs!$B$12 | G13: =Inputs!$B$12 | H13: =Inputs!$B$12 | I13: =Inputs!$B$12 | J13: =Inputs!$B$12 | ... N13: =Inputs!$B$12
A14: Other Operating | C14: =Inputs!$B$13 | D14: =Inputs!$B$13 | E14: =Inputs!$B$13 | F14: =Inputs!$B$13 | G14: =Inputs!$B$13 | H14: =Inputs!$B$13 | I14: =Inputs!$B$13 | J14: =Inputs!$B$13 | ... N14: =Inputs!$B$13
A15: Total Expenses | C15: =SUM(C10:C14) | D15: =SUM(D10:D14) | E15: =SUM(E10:E14) | F15: =SUM(F10:F14) | G15: =SUM(G10:G14) | H15: =SUM(H10:H14) | I15: =SUM(I10:I14) | J15: =SUM(J10:J14) | ... N15: =SUM(N10:N14)
A17: NET CASH FLOW | C17: =C7-C16 | D17: =D7-D16 | E17: =E7-E16 | F17: =F7-F16 | G17: =G7-G16 | H17: =H7-H16 | I17: =I7-I16 | J17: =J7-J16 | ... N17: =N7-N16
A18: ENDING CASH BALANCE | B18: =Inputs!$B$4 | C18: =B18+C17 | D18: =C18+D17 | E18: =D18+E17 | F18: =E18+F17 | G18: =F18+G17 | H18: =G18+H17 | I18: =H18+I17 | J18: =I18+J17 | ... N18: =M18+N17

Sheet Dashboard
A1: CASH FLOW DASHBOARD
A2: Executive Summary
A4: Metric | B4: Value
A5: Starting Cash | B5: =Inputs!B4
A6: Total Revenue (12 months) | B6: =SUM('12-Month Forecast'!C7:N7)
A7: Total Expenses (12 months) | B7: =SUM('12-Month Forecast'!C14:N14)
A8: Net Cash Flow (12 months) | B8: =B6-B7
A9: Ending Cash Balance | B9: ='12-Month Forecast'!N18
A10: Lowest Cash Point | B10: =MIN('12-Month Forecast'!C18:N18)
A13: CASH HEALTH CHECK
A14: Status: | B14: =IF(B9>B4*0.5,"✅ Healthy","⚠️ Monitor Closely")
A15: Runway (months): | B15: =B9/(B7/12)

Sheet How to Use
A1: HOW TO USE THIS FORECASTER
A4: STEP 1: Enter Your Data
A5: → Go to "Inputs" sheet
A6: → Fill in YELLOW cells with your numbers
A7: → Starting cash, revenue, expenses
A9: STEP 2: Review Forecast
A10: → Go to "12-Month Forecast" sheet
A11: → See your cash position for next 12 months
A12: → Check ending cash balance
A14: STEP 3: Check Dashboard
A15: → Go to "Dashboard" sheet
A16: → See summary metrics
... A30: Questions? Email: support@yoursite.com
